dagster_ducklake/__init__.py
dagster_ducklake/duckdb_file.py
dagster_ducklake/duckdb_protocol.py
dagster_ducklake/ducklake.py
dagster_ducklake-0.0.2.dist-info/METADATA
dagster_ducklake-0.0.2.dist-info/WHEEL
dagster_ducklake-0.0.2.dist-info/top_level.txt
dagster_ducklake-0.0.2.dist-info/RECORD
