Metadata-Version: 2.4
Name: dagster-ducklake
Version: 0.0.2
Summary: Dagster integration for Ducklake
Requires-Python: >=3.10
Requires-Dist: dagster>=1.11.9
Requires-Dist: duckdb>=1.4.0
Requires-Dist: pydantic>=2.0.0
Requires-Dist: sqlalchemy~=2.0.43
